tema1/ex1/or_gate.v
module or_gate(output o, input i1, i2, i3, i4, i5, i6, i7, i8);

assign o = i1 | i2 | i3 | i4 | i5 | i6 | i7 | i8;

endmodule

tema1/ex1/and_gate.v
module and_gate(output o, input i1, i2, i3, i4);

assign o = i1 & i2 & i3 & i4;

endmodule

tema1/ex1/not_gate.v
module not_gate(output o, input i);

assign o = ~ i;

endmodule

tema1/ex1/mux8_1.v
module m81(input IN0, IN1, IN2, IN3, IN4, IN5, IN6, IN7, S0, S1, S2, output Y); 
 
wire nS0, nS1, nS2, outa0, outa1, outa2, outa3, outa4, outa5, outa6, outa7;

not_gate ng0(nS0, S0);
not_gate ng1(nS1, S1);
not_gate ng2(nS2, S2);

and_gate ag0(outa0, IN0, nS0, nS1, nS2);
and_gate ag1(outa1, IN1, S0, nS1, nS2);
and_gate ag2(outa2, IN2, nS0, S1, nS2);
and_gate ag3(outa3, IN3, S0, S1, nS2);
and_gate ag4(outa4, IN4, nS0, nS1, S2);
and_gate ag5(outa5, IN5, S0, nS1, S2);
and_gate ag6(outa6, IN6, nS0, S1, S2);
and_gate ag7(outa7, IN7, S0, S1, S2);

or_gate og(Y, outa0, outa1, outa2, outa3, outa4, outa5, outa6, outa7);

endmodule

tema1/ex1/top.v
`include "mux8_1.v"
`include "and_gate.v"
`include "not_gate.v"
`include "or_gate.v"
module top; 

wire Y;
reg IN0, IN1, IN2, IN3, IN4, IN5, IN6, IN7, S0, S1, S2;

m81 mux(IN0, IN1, IN2, IN3, IN4, IN5, IN6, IN7, S0, S1, S2, Y);

initial $dumpfile("top.vcd");
initial $dumpvars(0, top);

initial 
	begin

	IN0=1'b0;
	IN1=1'b0;
	IN2=1'b0;
	IN3=1'b0;
	IN4=1'b0;
	IN5=1'b0;
	IN6=1'b0;
	IN7=1'b0;
	S0=1'b0;
	S1=1'b0;
	S2=1'b0; 

	#500 $finish; 
end 

	always #1 IN0=~IN0;
	always #2 IN1=~IN1;
	always #3 IN2=~IN2;
	always #4 IN3=~IN3;
	always #5 IN4=~IN4;
	always #6 IN5=~IN5;
	always #7 IN6=~IN6;
	always #8 IN7=~IN7;
	always #9 S0=~S0;
	always #10 S1=~S1;
	always #11 S2=~S2;

endmodule

tema1/ex1/top.vcd
$date
	Sat Oct 17 17:01:26 2020
$end
$version
	Icarus Verilog
$end
$timescale
	1s
$end
$scope module top $end
$var wire 1 ! Y $end
$var reg 1 " IN0 $end
$var reg 1 # IN1 $end
$var reg 1 $ IN2 $end
$var reg 1 % IN3 $end
$var reg 1 & IN4 $end
$var reg 1 ' IN5 $end
$var reg 1 ( IN6 $end
$var reg 1 ) IN7 $end
$var reg 1 * S0 $end
$var reg 1 + S1 $end
$var reg 1 , S2 $end
$scope module mux $end
$var wire 1 " IN0 $end
$var wire 1 # IN1 $end
$var wire 1 $ IN2 $end
$var wire 1 % IN3 $end
$var wire 1 & IN4 $end
$var wire 1 ' IN5 $end
$var wire 1 ( IN6 $end
$var wire 1 ) IN7 $end
$var wire 1 * S0 $end
$var wire 1 + S1 $end
$var wire 1 , S2 $end
$var wire 1 - outa7 $end
$var wire 1 . outa6 $end
$var wire 1 / outa5 $end
$var wire 1 0 outa4 $end
$var wire 1 1 outa3 $end
$var wire 1 2 outa2 $end
$var wire 1 3 outa1 $end
$var wire 1 4 outa0 $end
$var wire 1 5 nS2 $end
$var wire 1 6 nS1 $end
$var wire 1 7 nS0 $end
$var wire 1 ! Y $end
$scope module ag0 $end
$var wire 1 " i1 $end
$var wire 1 4 o $end
$var wire 1 5 i4 $end
$var wire 1 6 i3 $end
$var wire 1 7 i2 $end
$upscope $end
$scope module ag1 $end
$var wire 1 # i1 $end
$var wire 1 * i2 $end
$var wire 1 3 o $end
$var wire 1 5 i4 $end
$var wire 1 6 i3 $end
$upscope $end
$scope module ag2 $end
$var wire 1 $ i1 $end
$var wire 1 + i3 $end
$var wire 1 2 o $end
$var wire 1 5 i4 $end
$var wire 1 7 i2 $end
$upscope $end
$scope module ag3 $end
$var wire 1 % i1 $end
$var wire 1 * i2 $end
$var wire 1 + i3 $end
$var wire 1 1 o $end
$var wire 1 5 i4 $end
$upscope $end
$scope module ag4 $end
$var wire 1 & i1 $end
$var wire 1 , i4 $end
$var wire 1 0 o $end
$var wire 1 6 i3 $end
$var wire 1 7 i2 $end
$upscope $end
$scope module ag5 $end
$var wire 1 ' i1 $end
$var wire 1 * i2 $end
$var wire 1 , i4 $end
$var wire 1 / o $end
$var wire 1 6 i3 $end
$upscope $end
$scope module ag6 $end
$var wire 1 ( i1 $end
$var wire 1 + i3 $end
$var wire 1 , i4 $end
$var wire 1 . o $end
$var wire 1 7 i2 $end
$upscope $end
$scope module ag7 $end
$var wire 1 ) i1 $end
$var wire 1 * i2 $end
$var wire 1 + i3 $end
$var wire 1 , i4 $end
$var wire 1 - o $end
$upscope $end
$scope module ng0 $end
$var wire 1 * i $end
$var wire 1 7 o $end
$upscope $end
$scope module ng1 $end
$var wire 1 + i $end
$var wire 1 6 o $end
$upscope $end
$scope module ng2 $end
$var wire 1 , i $end
$var wire 1 5 o $end
$upscope $end
$scope module og $end
$var wire 1 4 i1 $end
$var wire 1 3 i2 $end
$var wire 1 2 i3 $end
$var wire 1 1 i4 $end
$var wire 1 0 i5 $end
$var wire 1 / i6 $end
$var wire 1 . i7 $end
$var wire 1 - i8 $end
$var wire 1 ! o $end
$upscope $end
$upscope $end
$upscope $end
$enddefinitions $end
#0
$dumpvars
17
16
15
04
03
02
01
00
0/
0.
0-
0,
0+
0*
0)
0(
0'
0&
0%
0$
0#
0"
0!
$end
#1
1!
14
1"
#2
0!
04
0"
1#
#3
1!
14
1"
1$
#4
0!
04
0"
0#
1%
#5
1!
14
1"
1&
#6
0!
04
0"
1#
0$
1'
#7
1!
14
1"
1(
#8
0!
04
0"
0#
0%
1)
#9
07
1"
1$
1*
#10
06
0"
1#
0&
1+
#11
1!
1-
05
1"
1,
#12
0"
0#
0$
1%
0'
#13
1"
#14
0"
1#
0(
#15
1"
1$
1&
#16
0!
0-
0"
0#
0%
0)
#17
1"
#18
17
0"
1#
0$
1'
0*
#19
1"
#20
16
0"
0#
1%
0&
0+
#21
1"
1$
1(
#22
0!
04
15
0"
1#
0,
#23
1!
14
1"
#24
0!
04
0"
0#
0$
0%
0'
1)
#25
1!
14
1"
1&
#26
0!
04
0"
1#
#27
1!
13
07
1"
1$
1*
#28
0!
03
0"
0#
1%
0(
#29
1"
#30
1!
11
06
0"
1#
0$
0&
1'
1+
#31
1"
#32
0!
01
0"
0#
0%
0)
#33
05
1"
1$
1,
#34
0"
1#
#35
1"
1&
1(
#36
1!
1.
17
0"
0#
0$
1%
0'
0*
#37
1"
#38
0"
1#
#39
1"
1$
#40
0!
0.
16
0"
0#
0%
0&
1)
0+
#41
1"
#42
0"
1#
0$
1'
0(
#43
1"
#44
0!
04
15
0"
0#
1%
0,
#45
07
1"
1$
1&
1*
#46
1!
13
0"
1#
#47
1"
#48
0!
03
0"
0#
0$
0%
0'
0)
#49
1"
1(
#50
06
0"
1#
0&
1+
#51
1"
1$
#52
1!
11
0"
0#
1%
#53
1"
#54
0!
01
17
0"
1#
0$
1'
0*
#55
1!
1.
05
1"
1&
1,
#56
0!
0.
0"
0#
0%
0(
1)
#57
1"
1$
#58
0"
1#
#59
1"
#60
16
0"
0#
0$
1%
0&
0'
0+
#61
1"
#62
0"
1#
#63
07
1"
1$
1(
1*
#64
0"
0#
0%
0)
#65
1"
1&
#66
1!
13
15
0"
1#
0$
1'
0,
#67
1"
#68
0!
03
0"
0#
1%
#69
1"
1$
#70
1!
11
06
0"
1#
0&
0(
1+
#71
1"
#72
0!
01
17
0"
0#
0$
0%
0'
1)
0*
#73
1"
#74
0"
1#
#75
1!
12
1"
1$
1&
#76
0"
0#
1%
#77
1.
02
05
1"
1(
1,
#78
0"
1#
0$
1'
#79
1"
#80
0!
0.
16
0"
0#
0%
0&
0)
0+
#81
1!
1/
07
1"
1$
1*
#82
0"
1#
#83
1"
#84
0!
0/
0"
0#
0$
1%
0'
0(
#85
1"
1&
#86
0"
1#
#87
1"
1$
#88
0!
03
15
0"
0#
0%
1)
0,
#89
1"
#90
17
06
0"
1#
0$
0&
1'
0*
1+
#91
1"
1(
#92
0"
0#
1%
#93
1!
12
1"
1$
#94
0"
1#
#95
1"
1&
#96
0!
02
0"
0#
0$
0%
0'
0)
#97
1"
#98
0"
1#
0(
#99
07
05
1"
1$
1*
1,
#100
16
0"
0#
1%
0&
0+
#101
1"
#102
1!
1/
0"
1#
0$
1'
#103
1"
#104
0"
0#
0%
1)
#105
1"
1$
1&
1(
#106
0"
1#
#107
1"
#108
1!
10
0/
17
0"
0#
0$
1%
0'
0*
#109
1"
#110
0!
04
06
00
15
0"
1#
0&
1+
0,
#111
1!
12
1"
1$
#112
0"
0#
0%
0(
0)
#113
1"
#114
0!
02
0"
1#
0$
1'
#115
1"
1&
#116
0"
0#
1%
#117
1!
11
07
1"
1$
1*
#118
0"
1#
#119
1"
1(
#120
0!
01
16
0"
0#
0$
0%
0&
0'
1)
0+
#121
05
1"
1,
#122
0"
1#
#123
1"
1$
#124
0"
0#
1%
#125
1"
1&
#126
1!
10
17
0"
1#
0$
1'
0(
0*
#127
1"
#128
0"
0#
0%
0)
#129
1"
1$
#130
0!
00
06
0"
1#
0&
1+
#131
1"
#132
0!
02
15
0"
0#
0$
1%
0'
0,
#133
1"
1(
#134
0"
1#
#135
1!
11
07
1"
1$
1&
1*
#136
0!
01
0"
0#
0%
1)
#137
1"
#138
0"
1#
0$
1'
#139
1"
#140
16
0"
0#
1%
0&
0(
0+
#141
1"
1$
#142
1!
13
0"
1#
#143
03
1/
05
1"
1,
#144
0!
0/
17
0"
0#
0$
0%
0'
0)
0*
#145
1!
10
1"
1&
#146
0"
1#
#147
1"
1$
1(
#148
0"
0#
1%
#149
1"
#150
00
1.
06
0"
1#
0$
0&
1'
1+
#151
1"
#152
0"
0#
0%
1)
#153
0.
1-
07
1"
1$
1*
#154
0!
0-
15
0"
1#
0(
0,
#155
1"
1&
#156
1!
11
0"
0#
0$
1%
0'
#157
1"
#158
0"
1#
#159
1"
1$
#160
0!
01
16
0"
0#
0%
0&
0)
0+
#161
1"
1(
#162
17
0"
1#
0$
1'
0*
#163
1!
14
1"
#164
0!
04
0"
0#
1%
#165
1!
10
05
1"
1$
1&
1,
#166
0"
1#
#167
1"
#168
0"
0#
0$
0%
0'
0(
1)
#169
1"
#170
0!
00
06
0"
1#
0&
1+
#171
1!
1-
07
1"
1$
1*
#172
0"
0#
1%
#173
1"
#174
0"
1#
0$
1'
#175
1"
1&
1(
#176
0!
01
0-
15
0"
0#
0%
0)
0,
#177
1"
1$
#178
0"
1#
#179
1"
#180
17
16
0"
0#
0$
1%
0&
0'
0*
0+
#181
1!
14
1"
#182
0!
04
0"
1#
0(
#183
1!
14
1"
1$
#184
0!
04
0"
0#
0%
1)
#185
1!
14
1"
1&
#186
0!
04
0"
1#
0$
1'
#187
1!
10
05
1"
1,
#188
0"
0#
1%
#189
00
1/
07
1"
1$
1(
1*
#190
0/
1-
06
0"
1#
0&
1+
#191
1"
#192
0!
0-
0"
0#
0$
0%
0'
0)
#193
1"
#194
0"
1#
#195
1"
1$
1&
#196
0"
0#
1%
0(
#197
1"
#198
0!
01
17
15
0"
1#
0$
1'
0*
0,
#199
1"
#200
16
0"
0#
0%
0&
1)
0+
#201
1!
14
1"
1$
#202
0!
04
0"
1#
#203
1!
14
1"
1(
#204
0!
04
0"
0#
0$
1%
0'
#205
1!
14
1"
1&
#206
0!
04
0"
1#
#207
1!
13
07
1"
1$
1*
#208
0!
03
0"
0#
0%
0)
#209
05
1"
1,
#210
06
0"
1#
0$
0&
1'
0(
1+
#211
1"
#212
0"
0#
1%
#213
1"
1$
#214
0"
1#
#215
1"
1&
#216
17
0"
0#
0$
0%
0'
1)
0*
#217
1!
1.
1"
1(
#218
0"
1#
#219
1"
1$
#220
0!
16
0.
15
0"
0#
1%
0&
0+
0,
#221
1!
14
1"
#222
0!
04
0"
1#
0$
1'
#223
1!
14
1"
#224
0!
04
0"
0#
0%
0(
0)
#225
07
1"
1$
1&
1*
#226
1!
13
0"
1#
#227
1"
#228
0!
03
0"
0#
0$
1%
0'
#229
1"
#230
1!
11
06
0"
1#
0&
1+
#231
0!
01
05
1"
1$
1(
1,
#232
1!
1-
0"
0#
0%
1)
#233
1"
#234
1!
1.
0-
17
0"
1#
0$
1'
0*
#235
1"
1&
#236
0"
0#
1%
#237
1"
1$
#238
0!
0.
0"
1#
0(
#239
1"
#240
16
0"
0#
0$
0%
0&
0'
0)
0+
#241
1"
#242
0!
04
15
0"
1#
0,
#243
1!
13
07
1"
1$
1*
#244
0!
03
0"
0#
1%
#245
1"
1&
1(
#246
1!
13
0"
1#
0$
1'
#247
1"
#248
0!
03
0"
0#
0%
1)
#249
1"
1$
#250
06
0"
1#
0&
1+
#251
1"
#252
17
0"
0#
0$
1%
0'
0(
0*
#253
05
1"
1,
#254
0"
1#
#255
1"
1$
1&
#256
0"
0#
0%
0)
#257
1"
#258
0"
1#
0$
1'
#259
1!
1.
1"
1(
#260
0!
0.
16
0"
0#
1%
0&
0+
#261
1!
1/
07
1"
1$
1*
#262
0"
1#
#263
1"
#264
0!
03
0/
15
0"
0#
0$
0%
0'
1)
0,
#265
1"
1&
#266
1!
13
0"
1#
0(
#267
1"
1$
#268
0!
03
0"
0#
1%
#269
1"
#270
0!
01
17
06
0"
1#
0$
0&
1'
0*
1+
#271
1"
#272
0"
0#
0%
0)
#273
1!
12
1"
1$
1(
#274
0"
1#
#275
02
1.
05
1"
1&
1,
#276
0"
0#
0$
1%
0'
#277
1"
#278
0"
1#
#279
0!
0.
07
1"
1$
1*
#280
16
0"
0#
0%
0&
0(
1)
0+
#281
1"
#282
1!
1/
0"
1#
0$
1'
#283
1"
#284
0"
0#
1%
#285
1"
1$
1&
#286
1!
13
0/
15
0"
1#
0,
#287
1"
1(
#288
0!
03
17
0"
0#
0$
0%
0'
0)
0*
#289
1!
14
1"
#290
0!
04
06
0"
1#
0&
1+
#291
1!
12
1"
1$
#292
0"
0#
1%
#293
1"
#294
0!
02
0"
1#
0$
1'
0(
#295
1"
1&
#296
0"
0#
0%
1)
#297
1!
1-
07
05
1"
1$
1*
1,
#298
0"
1#
#299
1"
#300
0!
0-
16
0"
0#
0$
1%
0&
0'
0+
#301
1"
1(
#302
0"
1#
#303
1"
1$
#304
0"
0#
0%
0)
#305
1"
1&
#306
1!
10
17
0"
1#
0$
1'
0*
#307
1"
#308
0!
04
00
15
0"
0#
1%
0(
0,
#309
1!
14
1"
1$
#310
04
12
06
0"
1#
0&
1+
#311
1"
#312
0!
02
0"
0#
0$
0%
0'
1)
#313
1"
#314
0"
1#
#315
07
1"
1$
1&
1(
1*
#316
1!
11
0"
0#
1%
#317
1"
#318
0"
1#
0$
1'
#319
01
1-
05
1"
1,
#320
1!
1/
0-
16
0"
0#
0%
0&
0)
0+
#321
1"
1$
#322
0"
1#
0(
#323
1"
#324
0!
0/
17
0"
0#
0$
1%
0'
0*
#325
1!
10
1"
1&
#326
0"
1#
#327
1"
1$
#328
0"
0#
0%
1)
#329
1"
1(
#330
0!
02
04
06
00
15
0"
1#
0$
0&
1'
1+
0,
#331
1"
#332
0"
0#
1%
#333
1!
11
07
1"
1$
1*
#334
0"
1#
#335
1"
1&
#336
0!
01
0"
0#
0$
0%
0'
0(
0)
#337
1"
#338
0"
1#
#339
1"
1$
#340
16
0"
0#
1%
0&
0+
#341
05
1"
1,
#342
17
0"
1#
0$
1'
0*
#343
1"
1(
#344
0"
0#
0%
1)
#345
1!
10
1"
1$
1&
#346
0"
1#
#347
1"
#348
0"
0#
0$
1%
0'
#349
1"
#350
0!
00
0.
06
0"
1#
0&
0(
1+
#351
1!
1-
07
1"
1$
1*
#352
0!
01
0-
15
0"
0#
0%
0)
0,
#353
1"
#354
0"
1#
0$
1'
#355
1"
1&
#356
1!
11
0"
0#
1%
#357
1"
1$
1(
#358
0"
1#
#359
1"
#360
0!
01
17
16
0"
0#
0$
0%
0&
0'
1)
0*
0+
#361
1!
14
1"
#362
0!
04
0"
1#
#363
05
1"
1$
1,
#364
0"
0#
1%
0(
#365
1!
10
1"
1&
#366
0"
1#
0$
1'
#367
1"
#368
0"
0#
0%
0)
#369
00
1/
07
1"
1$
1*
#370
0!
0/
06
0"
1#
0&
1+
#371
1"
1(
#372
0"
0#
0$
1%
0'
#373
1"
#374
1!
11
15
0"
1#
0,
#375
1"
1$
1&
#376
0!
01
0"
0#
0%
1)
#377
1"
#378
17
0"
1#
0$
1'
0(
0*
#379
1"
#380
16
0"
0#
1%
0&
0+
#381
1!
14
1"
1$
#382
0!
04
0"
1#
#383
1!
14
1"
#384
0!
04
0"
0#
0$
0%
0'
0)
#385
1!
10
05
1"
1&
1(
1,
#386
0"
1#
#387
0!
00
07
1"
1$
1*
#388
0"
0#
1%
#389
1"
#390
06
0"
1#
0$
0&
1'
1+
#391
1"
#392
1!
1-
0"
0#
0%
0(
1)
#393
1"
1$
#394
0"
1#
#395
1"
1&
#396
0!
17
0-
15
0"
0#
0$
1%
0'
0*
0,
#397
1"
#398
0"
1#
#399
1!
12
1"
1$
1(
#400
0!
02
16
0"
0#
0%
0&
0)
0+
#401
1!
14
1"
#402
0!
04
0"
1#
0$
1'
#403
1!
14
1"
#404
0!
04
0"
0#
1%
#405
07
1"
1$
1&
1*
#406
1!
13
0"
1#
0(
#407
03
1/
05
1"
1,
#408
0!
0/
0"
0#
0$
0%
0'
1)
#409
1"
#410
1!
1-
06
0"
1#
0&
1+
#411
1"
1$
#412
0"
0#
1%
#413
1"
1(
#414
1!
1.
0-
17
0"
1#
0$
1'
0*
#415
1"
1&
#416
0"
0#
0%
0)
#417
1"
1$
#418
1!
12
0.
15
0"
1#
0,
#419
1"
#420
0!
02
16
0"
0#
0$
1%
0&
0'
0(
0+
#421
1!
14
1"
#422
0!
04
0"
1#
#423
1!
13
07
1"
1$
1*
#424
0!
03
0"
0#
0%
1)
#425
1"
1&
#426
1!
13
0"
1#
0$
1'
#427
1"
1(
#428
0!
03
0"
0#
1%
#429
1!
1/
05
1"
1$
1,
#430
0/
1-
06
0"
1#
0&
1+
#431
1"
#432
1!
1.
0-
17
0"
0#
0$
0%
0'
0)
0*
#433
1"
#434
0!
0.
0"
1#
0(
#435
1"
1$
1&
#436
0"
0#
1%
#437
1"
#438
0"
1#
0$
1'
#439
1"
#440
16
15
0"
0#
0%
0&
1)
0+
0,
#441
07
1"
1$
1(
1*
#442
1!
13
0"
1#
#443
1"
#444
0!
03
0"
0#
0$
1%
0'
#445
1"
1&
#446
1!
13
0"
1#
#447
1"
1$
#448
0!
03
0"
0#
0%
0(
0)
#449
1"
#450
17
06
0"
1#
0$
0&
1'
0*
1+
#451
05
1"
1,
#452
0"
0#
1%
#453
1"
1$
#454
0"
1#
#455
1!
1.
1"
1&
1(
#456
0"
0#
0$
0%
0'
1)
#457
1"
#458
0"
1#
#459
0.
1-
07
1"
1$
1*
#460
0!
0-
16
0"
0#
1%
0&
0+
#461
1"
#462
1!
13
15
0"
1#
0$
1'
0(
0,
#463
1"
#464
0!
03
0"
0#
0%
0)
#465
1"
1$
1&
#466
1!
13
0"
1#
#467
1"
#468
0!
03
17
0"
0#
0$
1%
0'
0*
#469
1!
14
1"
1(
#470
0!
04
06
0"
1#
0&
1+
#471
1!
12
1"
1$
#472
0"
0#
0%
1)
#473
02
1.
05
1"
1,
#474
0"
1#
0$
1'
#475
1"
1&
#476
0!
0.
0"
0#
1%
0(
#477
1!
1-
07
1"
1$
1*
#478
0"
1#
#479
1"
#480
0!
0-
16
0"
0#
0$
0%
0&
0'
0)
0+
#481
1"
#482
0"
1#
#483
1"
1$
1(
#484
0!
03
15
0"
0#
1%
0,
#485
1"
1&
#486
17
0"
1#
0$
1'
0*
#487
1!
14
1"
#488
0!
04
0"
0#
0%
1)
#489
1!
14
1"
1$
#490
04
12
06
0"
1#
0&
0(
1+
#491
1"
#492
0!
02
0"
0#
0$
1%
0'
#493
1"
#494
0"
1#
#495
1!
1-
07
05
1"
1$
1&
1*
1,
#496
0!
0-
0"
0#
0%
0)
#497
1"
1(
#498
0"
1#
0$
1'
#499
1"
#500
1!
1/
16
0"
0#
1%
0&
0+
